.DS_Store
methylize/__init__.py
methylize/__main__.py
methylize/combined_pvalues.py
methylize/diff_meth_pos.py
methylize/diff_meth_regions.py
methylize/genome_browser.py
methylize/helpers.py
methylize/progress_bar.py
methylize/test.py
methylize/version.py
methylize/cpv/__init__.py
methylize/cpv/_common.py
methylize/cpv/acf.py
methylize/cpv/fdr.py
methylize/cpv/filter.py
methylize/cpv/hist.py
methylize/cpv/manhattan.py
methylize/cpv/peaks.py
methylize/cpv/pipeline.py
methylize/cpv/qvality.py
methylize/cpv/region_p.py
methylize/cpv/slk.py
methylize/cpv/stepsize.py
methylize/cpv/stouffer_liptak.py
methylize/data/__init__.py
tests/__init__.py
tests/test_analysis.py
tests/test_diff_meth_regions.py
tests/test_genome_browser.py
methylize-1.1.1.dist-info/LICENSE.txt
methylize-1.1.1.dist-info/METADATA
methylize-1.1.1.dist-info/WHEEL
methylize-1.1.1.dist-info/entry_points.txt
methylize-1.1.1.dist-info/top_level.txt
methylize-1.1.1.dist-info/RECORD
