Metadata-Version: 2.1
Name: methylize
Version: 1.1.1
Summary: EWAS Analysis software for Illumina methylation arrays
Home-page: https://github.com/FOXOBioScience/methylize
Author: FOXO Bioscience
Author-email: info@FOXOBioScience.com
License: MIT
Project-URL: Documentation, https://life-epigenetics-methylize.readthedocs-hosted.com/en/latest/
Project-URL: Source, https://github.com/FOXOBioScience/methylize/
Project-URL: Funding, https://FOXOBioScience.com/
Keywords: analysis methylation dna data processing life epigenetics illumina parallelization
Platform: UNKNOWN
Classifier: Development Status :: 5 - Production/Stable
Classifier: Environment :: Console
Classifier: License :: OSI Approved :: MIT License
Classifier: Programming Language :: Python :: 3.8
Classifier: Topic :: Scientific/Engineering :: Bio-Informatics
Classifier: Topic :: Scientific/Engineering :: Medical Science Apps.
Classifier: Framework :: Jupyter
Classifier: Intended Audience :: Science/Research
Classifier: Intended Audience :: Financial and Insurance Industry
Classifier: Operating System :: MacOS :: MacOS X
Classifier: Operating System :: Microsoft :: Windows
Classifier: Operating System :: POSIX :: Linux
Requires-Dist: pandas
Requires-Dist: numpy
Requires-Dist: scipy
Requires-Dist: statsmodels
Requires-Dist: matplotlib
Requires-Dist: methylprep
Requires-Dist: pymysql
Requires-Dist: toolshed
Requires-Dist: interlap
Requires-Dist: adjustText
Requires-Dist: joblib
Requires-Dist: seaborn
Provides-Extra: dev
Requires-Dist: pytest ; extra == 'dev'
Requires-Dist: coverage ; extra == 'dev'
